{
    "apple_pie": 237,
    "baby_back_ribs": 252,
    "baklava": 428,
    "beef_carpaccio": 160,
    "beef_tartare": 210,
    "beet_salad": 95,
    "beignets": 320,
    "bibimbap": 165,
    "bread_pudding": 310,
    "breakfast_burrito": 230,
    "bruschetta": 175,
    "caesar_salad": 180,
    "cannoli": 330,
    "caprese_salad": 190,
    "carrot_cake": 415,
    "ceviche": 120,
    "cheesecake": 321,
    "cheese_plate": 350,
    "chicken_curry": 140,
    "chicken_quesadilla": 275,
    "chicken_wings": 203,
    "chocolate_cake": 371,
    "chocolate_mousse": 225,
    "churros": 281,
    "clam_chowder": 110,
    "club_sandwich": 220,
    "crab_cakes": 210,
    "creme_brulee": 300,
    "croque_madame": 280,
    "cup_cakes": 305,
    "deviled_eggs": 200,
    "donuts": 452,
    "dumplings": 150,
    "edamame": 121,
    "eggs_benedict": 260,
    "escargots": 140,
    "falafel": 333,
    "filet_mignon": 267,
    "fish_and_chips": 250,
    "foie_gras": 462,
    "french_fries": 312,
    "french_onion_soup": 90,
    "french_toast": 229,
    "fried_calamari": 175,
    "fried_rice": 163,
    "frozen_yogurt": 159,
    "garlic_bread": 350,
    "gnocchi": 133,
    "greek_salad": 105,
    "grilled_cheese_sandwich": 335,
    "grilled_salmon": 208,
    "guacamole": 160,
    "gyoza": 150,
    "hamburger": 295,
    "hot_and_sour_soup": 39,
    "hot_dog": 290,
    "huevos_rancheros": 220,
    "hummus": 166,
    "ice_cream": 207,
    "lasagna": 135,
    "lobster_bisque": 140,
    "lobster_roll_sandwich": 210,
    "macaroni_and_cheese": 164,
    "macarons": 420,
    "miso_soup": 35,
    "mussels": 172,
    "nachos": 343,
    "omelette": 154,
    "onion_rings": 411,
    "oysters": 68,
    "pad_thai": 175,
    "paella": 160,
    "pancakes": 227,
    "panna_cotta": 240,
    "peking_duck": 337,
    "pho": 100,
    "pizza": 266,
    "pork_chop": 231,
    "poutine": 280,
    "prime_rib": 340,
    "pulled_pork_sandwich": 235,
    "ramen": 120,
    "ravioli": 160,
    "red_velvet_cake": 375,
    "risotto": 150,
    "samosa": 262,
    "sashimi": 130,
    "scallops": 111,
    "seaweed_salad": 45,
    "shrimp_and_grits": 140,
    "spaghetti_bolognese": 130,
    "spaghetti_carbonara": 220,
    "spring_rolls": 180,
    "steak": 271,
    "strawberry_shortcake": 340,
    "sushi": 143,
    "tacos": 226,
    "takoyaki": 150,
    "tiramisu": 283,
    "tuna_tartare": 150,
    "waffles": 291
}
